feedsearch_crawler/__init__.py
feedsearch_crawler/crawler/__init__.py
feedsearch_crawler/crawler/crawler.py
feedsearch_crawler/crawler/downloader.py
feedsearch_crawler/crawler/duplicatefilter.py
feedsearch_crawler/crawler/exceptions.py
feedsearch_crawler/crawler/item.py
feedsearch_crawler/crawler/item_parser.py
feedsearch_crawler/crawler/lib.py
feedsearch_crawler/crawler/middleware/__init__.py
feedsearch_crawler/crawler/middleware/base.py
feedsearch_crawler/crawler/middleware/content_type.py
feedsearch_crawler/crawler/middleware/cookie.py
feedsearch_crawler/crawler/middleware/monitoring.py
feedsearch_crawler/crawler/middleware/retry.py
feedsearch_crawler/crawler/middleware/robots.py
feedsearch_crawler/crawler/middleware/throttle.py
feedsearch_crawler/crawler/queueable.py
feedsearch_crawler/crawler/request.py
feedsearch_crawler/crawler/response.py
feedsearch_crawler/crawler/statistics.py
feedsearch_crawler/crawler/trace.py
feedsearch_crawler/exceptions.py
feedsearch_crawler/feed_spider/__init__.py
feedsearch_crawler/feed_spider/dupefilter.py
feedsearch_crawler/feed_spider/favicon.py
feedsearch_crawler/feed_spider/feed_info.py
feedsearch_crawler/feed_spider/feed_info_parser.py
feedsearch_crawler/feed_spider/lib.py
feedsearch_crawler/feed_spider/link_filter.py
feedsearch_crawler/feed_spider/regexes.py
feedsearch_crawler/feed_spider/site_meta.py
feedsearch_crawler/feed_spider/site_meta_parser.py
feedsearch_crawler/feed_spider/spider.py
feedsearch_crawler/py.typed
feedsearch_crawler/result.py
feedsearch_crawler/schemas.py
feedsearch_crawler-2.0.1.dist-info/WHEEL
feedsearch_crawler-2.0.1.dist-info/entry_points.txt
feedsearch_crawler-2.0.1.dist-info/METADATA
feedsearch_crawler-2.0.1.dist-info/RECORD
