Metadata-Version: 2.4
Name: feedsearch-crawler
Version: 2.0.1
Summary: Search sites for RSS, Atom, and JSON feeds
Keywords: RSS,Search,Crawler,Feeds,Atom
Author: David Beath
Author-email: David Beath <davidgbeath@gmail.com>
License-Expression: MIT
Classifier: License :: OSI Approved :: MIT License
Classifier: Intended Audience :: Developers
Classifier: Development Status :: 5 - Production/Stable
Classifier: Natural Language :: English
Classifier: Operating System :: POSIX
Classifier: Operating System :: Microsoft :: Windows
Classifier: Operating System :: MacOS :: MacOS X
Classifier: Programming Language :: Python :: 3.12
Classifier: Programming Language :: Python :: 3.13
Classifier: Topic :: Internet :: WWW/HTTP :: Indexing/Search
Classifier: Typing :: Typed
Classifier: Framework :: AsyncIO
Requires-Dist: aiohttp>3.13.0
Requires-Dist: beautifulsoup4>=4.14.2
Requires-Dist: aiodns>=3.2.0
Requires-Dist: uvloop>=0.19.0
Requires-Dist: w3lib>=2.1.2
Requires-Dist: feedparser>=6.0.12
Requires-Dist: brotlipy>=0.7.0
Requires-Dist: python-dateutil>=2.9.0.post0
Requires-Dist: yarl>=1.22.0
Requires-Dist: asyncio>=3.4.3
Requires-Python: >=3.12
